{
    "type": "bp",
    "id": "8405",
    "name": "[AG] 행운의 BP 카드 (750억~1000억 BP)",
    "image": null,
    "expectedBp": 85484848476.3,
    "expectedValue": {
        "bp_card": 85484848476.3
    },
    "percentile": {
        "0": 100000000000,
        "1": 100000000000,
        "2": 99000000000,
        "5": 97000000000,
        "10": 94000000000,
        "20": 91000000000,
        "30": 89000000000,
        "40": 87000000000,
        "50": 85000000000,
        "60": 83000000000,
        "70": 82000000000,
        "80": 80000000000,
        "90": 77000000000,
        "100": 75000000000
    },
    "itemList": [
        {
            "amount": 1,
            "value": 100000000000,
            "prob": 0.0101010101
        },
        {
            "amount": 1,
            "value": 99000000000,
            "prob": 0.0101010101
        },
        {
            "amount": 1,
            "value": 98000000000,
            "prob": 0.0101010101
        },
        {
            "amount": 1,
            "value": 97000000000,
            "prob": 0.0202020202
        },
        {
            "amount": 1,
            "value": 96000000000,
            "prob": 0.0202020202
        },
        {
            "amount": 1,
            "value": 95000000000,
            "prob": 0.0202020202
        },
        {
            "amount": 1,
            "value": 94000000000,
            "prob": 0.0303030303
        },
        {
            "amount": 1,
            "value": 93000000000,
            "prob": 0.0303030303
        },
        {
            "amount": 1,
            "value": 92000000000,
            "prob": 0.0303030303
        },
        {
            "amount": 1,
            "value": 91000000000,
            "prob": 0.0404040404
        },
        {
            "amount": 1,
            "value": 90000000000,
            "prob": 0.0404040404
        },
        {
            "amount": 1,
            "value": 89000000000,
            "prob": 0.0404040404
        },
        {
            "amount": 1,
            "value": 88000000000,
            "prob": 0.0505050505
        },
        {
            "amount": 1,
            "value": 87000000000,
            "prob": 0.0505050505
        },
        {
            "amount": 1,
            "value": 86000000000,
            "prob": 0.0505050505
        },
        {
            "amount": 1,
            "value": 85000000000,
            "prob": 0.0707070707
        },
        {
            "amount": 1,
            "value": 84000000000,
            "prob": 0.0707070707
        },
        {
            "amount": 1,
            "value": 83000000000,
            "prob": 0.0707070707
        },
        {
            "amount": 1,
            "value": 82000000000,
            "prob": 0.0505050505
        },
        {
            "amount": 1,
            "value": 81000000000,
            "prob": 0.0505050505
        },
        {
            "amount": 1,
            "value": 80000000000,
            "prob": 0.0505050505
        },
        {
            "amount": 1,
            "value": 79000000000,
            "prob": 0.0404040404
        },
        {
            "amount": 1,
            "value": 78000000000,
            "prob": 0.0404040404
        },
        {
            "amount": 1,
            "value": 77000000000,
            "prob": 0.0404040404
        },
        {
            "amount": 1,
            "value": 76000000000,
            "prob": 0.0303030303
        },
        {
            "amount": 1,
            "value": 75000000000,
            "prob": 0.0303030303
        }
    ]
}