{
    "type": "bp",
    "id": "7882",
    "name": "[AG] 행운의 BP 카드 (680억~1080억 BP)",
    "image": null,
    "expectedBp": 87999999991.20001,
    "expectedValue": {
        "bp_card": 87999999991.20001
    },
    "percentile": {
        "0": 108000000000,
        "1": 108000000000,
        "2": 108000000000,
        "5": 104000000000,
        "10": 102000000000,
        "20": 96000000000,
        "30": 94000000000,
        "40": 90000000000,
        "50": 88000000000,
        "60": 86000000000,
        "70": 82000000000,
        "80": 80000000000,
        "90": 74000000000,
        "100": 68000000000
    },
    "itemList": [
        {
            "amount": 1,
            "value": 108000000000,
            "prob": 0.0208333333
        },
        {
            "amount": 1,
            "value": 106000000000,
            "prob": 0.0208333333
        },
        {
            "amount": 1,
            "value": 104000000000,
            "prob": 0.0208333333
        },
        {
            "amount": 1,
            "value": 102000000000,
            "prob": 0.041666666699999994
        },
        {
            "amount": 1,
            "value": 100000000000,
            "prob": 0.041666666699999994
        },
        {
            "amount": 1,
            "value": 98000000000,
            "prob": 0.041666666699999994
        },
        {
            "amount": 1,
            "value": 96000000000,
            "prob": 0.0625
        },
        {
            "amount": 1,
            "value": 94000000000,
            "prob": 0.0625
        },
        {
            "amount": 1,
            "value": 92000000000,
            "prob": 0.0625
        },
        {
            "amount": 1,
            "value": 90000000000,
            "prob": 0.0833333333
        },
        {
            "amount": 1,
            "value": 88000000000,
            "prob": 0.0833333333
        },
        {
            "amount": 1,
            "value": 86000000000,
            "prob": 0.0833333333
        },
        {
            "amount": 1,
            "value": 84000000000,
            "prob": 0.0625
        },
        {
            "amount": 1,
            "value": 82000000000,
            "prob": 0.0625
        },
        {
            "amount": 1,
            "value": 80000000000,
            "prob": 0.0625
        },
        {
            "amount": 1,
            "value": 78000000000,
            "prob": 0.041666666699999994
        },
        {
            "amount": 1,
            "value": 76000000000,
            "prob": 0.041666666699999994
        },
        {
            "amount": 1,
            "value": 74000000000,
            "prob": 0.041666666699999994
        },
        {
            "amount": 1,
            "value": 72000000000,
            "prob": 0.0208333333
        },
        {
            "amount": 1,
            "value": 70000000000,
            "prob": 0.0208333333
        },
        {
            "amount": 1,
            "value": 68000000000,
            "prob": 0.0208333333
        }
    ]
}