{
    "type": "box",
    "id": "8151",
    "name": "[마일리지] 아이스 캡 상자",
    "image": "201704553_s",
    "expectedBp": 158416368984.2702,
    "expectedValue": {
        "bp_player": 172191705417.685
    },
    "percentile": {
        "0": 7580800000000.0,
        "1": 797640000000.0,
        "2": 644000000000.0,
        "5": 362480000000.0,
        "10": 253920000000.0,
        "20": 183080000000.0,
        "30": 147200000000.0,
        "40": 122360000000.0,
        "50": 106720000000.0,
        "60": 98440000000.0,
        "70": 94760000000.0,
        "80": 90160000000.0,
        "90": 78660000000.0,
        "100": 67988000000.0
    },
    "itemList": [
        {
            "item": {
                "type": "player-pack",
                "id": "8144",
                "name": "[마일리지] DC, JVA, CC 포함 Top Price 180 (5강, 104+)",
                "image": null,
                "expectedBp": 154450179575.1784,
                "expectedValue": {
                    "bp_player": 167880629973.02
                }
            },
            "amount": 1,
            "prob": 0.45
        },
        {
            "item": {
                "type": "player-pack",
                "id": "8145",
                "name": "[마일리지] 23HW, HG, RTN, 22UCL Top Price 460 (7강, 97+)",
                "image": null,
                "expectedBp": 161661433046.25443,
                "expectedValue": {
                    "bp_player": 175718948963.32
                }
            },
            "amount": 1,
            "prob": 0.55
        }
    ]
}